server/__init__.py
server/db_analytics.py
server/db_analytics_core.py
mcp_postgress_server-0.1.0.dist-info/METADATA
mcp_postgress_server-0.1.0.dist-info/WHEEL
mcp_postgress_server-0.1.0.dist-info/top_level.txt
mcp_postgress_server-0.1.0.dist-info/RECORD
