Metadata-Version: 2.4
Name: mcp-postgress-server
Version: 0.1.0
Summary: Add your description here
Home-page: https://github.com/SwiftAlice/mcp_postgress_server.git
Author: Nancy Madan
Author-email: nancymadan.6@gmail.com
Requires-Python: >=3.9
Requires-Dist: mcp[cli]>=1.9.2
Dynamic: author
Dynamic: author-email
Dynamic: home-page
Dynamic: requires-python
